PyPark/API.py
PyPark/api_doc.py
PyPark/config.py
PyPark/cons.py
PyPark/lock.py
PyPark/logger.py
PyPark/my_thread.py
PyPark/park.py
PyPark/park_exception.py
PyPark/park_zk.py
PyPark/pydebug.py
PyPark/rest.py
PyPark/result.py
PyPark/result_redis.py
PyPark/strategy.py
PyPark/version.py
PyPark/watch.py
PyPark/zk.py
PyPark/nat/master.py
PyPark/nat/slaver.py
PyPark/shootback/common_func.py
PyPark/shootback/master.py
PyPark/shootback/slaver.py
PyPark/util/file.py
PyPark/util/json_to.py
PyPark/util/net.py
PyPark/util/util.py
PyPark/util/zk_util.py
PyPark-0.0.10.dist-info/LICENSE
PyPark-0.0.10.dist-info/METADATA
PyPark-0.0.10.dist-info/WHEEL
PyPark-0.0.10.dist-info/top_level.txt
PyPark-0.0.10.dist-info/RECORD
