Metadata-Version: 2.1
Name: PyPark
Version: 0.0.10
Summary: PyPark
Home-page: https://github.com/liuzhuogood/PyPark
Author: liuzhuogood
Author-email: liuzhuogood@foxmail.com
License: UNKNOWN
Download-URL: https://github.com/liuzhuogood/PyPark
Platform: UNKNOWN
Requires-Dist: tornado (~=6.1)
Requires-Dist: PyYAML (~=5.3.1)
Requires-Dist: kazoo (~=2.8.0)
Requires-Dist: requests (~=2.25.0)
Requires-Dist: ruamel.yaml
